ai/__init__.py
ai/open_ai.py
ai/tokens.py
core/__init__.py
core/config.py
core/main.py
data/__init__.py
data/chroma.py
data/database.py
data/file_sections.py
data/files.py
data/indexes.py
data/projects.py
data/query.py
index/__init__.py
index/embeddings.py
index/file_processor.py
repository/__init__.py
repository/file_sections.py
repository/files.py
repository/indexes.py
repository/projects.py
gpt_code_assistant-0.0.1.dist-info/LICENSE
gpt_code_assistant-0.0.1.dist-info/METADATA
gpt_code_assistant-0.0.1.dist-info/WHEEL
gpt_code_assistant-0.0.1.dist-info/entry_points.txt
gpt_code_assistant-0.0.1.dist-info/RECORD
