Metadata-Version: 2.1
Name: gpt-code-assistant
Version: 0.0.1
Summary: gpt-code-assistant is an intelligent coding assistant leveraging language models to search, retrieve, explore and comprehend your codebase.
Home-page: https://github.com/narenmanoharan/gpt-code-assistant
License: Apache-2.0
Keywords: gpt,code,search,gpt4,llm
Author: narenmanoharan
Author-email: narenkmanoharan@gmail.com
Requires-Python: >=3.8.17,<4.0.0
Classifier: License :: OSI Approved :: Apache Software License
Classifier: Programming Language :: Python :: 3
Classifier: Programming Language :: Python :: 3.9
Classifier: Programming Language :: Python :: 3.10
Classifier: Programming Language :: Python :: 3.11
Requires-Dist: chromadb (>=0.4.0,<0.5.0)
Requires-Dist: halo (>=0.0.31,<0.0.32)
Requires-Dist: openai (>=0.27.8,<0.28.0)
Requires-Dist: requests (>=2.31.0,<3.0.0)
Requires-Dist: rich (>=13.4.2,<14.0.0)
Requires-Dist: scikit-learn (>=1.2.2,<2.0.0)
Requires-Dist: sqlalchemy-pydantic (>=0.0.7,<0.0.8)
Requires-Dist: sqlalchemy-utils (>=0.41.1,<0.42.0)
Requires-Dist: tenacity (>=8.2.2,<9.0.0)
Requires-Dist: termcolor (>=2.3.0,<3.0.0)
Requires-Dist: tiktoken (>=0.4.0,<0.5.0)
Requires-Dist: toml (>=0.10.2,<0.11.0)
Requires-Dist: tqdm (>=4.65.0,<5.0.0)
Requires-Dist: typer[all] (>=0.9.0,<0.10.0)
Project-URL: Repository, https://github.com/narenmanoharan/gpt-code-assistant
Project-URL: discussions, https://github.com/narenmanoharan/gpt-code-assistant/discussions
Project-URL: issues, https://github.com/narenmanoharan/gpt-code-assistant/issues
Project-URL: wiki, https://github.com/narenmanoharan/gpt-code-assistant/wiki
